stock/__init__.py
stock/stock_quote.py
stock_quote_cli-1.0.0.dist-info/DESCRIPTION.rst
stock_quote_cli-1.0.0.dist-info/METADATA
stock_quote_cli-1.0.0.dist-info/RECORD
stock_quote_cli-1.0.0.dist-info/WHEEL
stock_quote_cli-1.0.0.dist-info/entry_points.txt
stock_quote_cli-1.0.0.dist-info/metadata.json
stock_quote_cli-1.0.0.dist-info/top_level.txt
