Metadata-Version: 2.0
Name: stock-quote-cli
Version: 1.0.0
Summary: show stock info
Home-page: https://github.com/yvvarun/stock-quote-cli
Author: yvvarun
Author-email: yvvarun@gmail.com
License: UNKNOWN
Platform: UNKNOWN
Classifier: Programming Language :: Python :: 2
Classifier: License :: OSI Approved :: MIT License
Classifier: Operating System :: OS Independent
